backpedal/__init__.py
backpedal-0.9.14.dist-info/LICENSE
backpedal-0.9.14.dist-info/METADATA
backpedal-0.9.14.dist-info/WHEEL
backpedal-0.9.14.dist-info/top_level.txt
backpedal-0.9.14.dist-info/RECORD
