Metadata-Version: 2.1
Name: backpedal
Version: 0.9.14
Summary: Backpedal
Home-page: http://github.com/datafolklabs/backpedal
Author: BJ Dierkes
Author-email: derks@datafolklabs.com
License: BSD-three-clause
Platform: UNKNOWN
License-File: LICENSE
